text2config/__init__.py
text2config/main.py
text2config/cli/__init__.py
text2config/pkg/__init__.py
text2config/pkg/openai/__init__.py
text2config/pkg/openai/prompts.py
text2config/pkg/openai/templates/docker.tpl
text2config/pkg/openai/templates/k8s-cmd.tpl
text2config/pkg/openai/templates/k8s-yaml.tpl
text2config/pkg/openai/templates/nginx.tpl
text2config-0.0.1.dist-info/LICENSE
text2config-0.0.1.dist-info/METADATA
text2config-0.0.1.dist-info/WHEEL
text2config-0.0.1.dist-info/entry_points.txt
text2config-0.0.1.dist-info/top_level.txt
text2config-0.0.1.dist-info/RECORD
