Metadata-Version: 2.1
Name: text2config
Version: 0.0.1
Summary: text to config or command
Home-page: https://github.com/FingerLiu/text2config
Author: liupeng
Author-email: liupeng.dalian@gmail.com
License-File: LICENSE
Requires-Dist: langchain
Requires-Dist: openai
Requires-Dist: azure-core
Requires-Dist: google-search-results
